.mina/standard-qq.toml
avilla/standard/qq/announcement/__init__.py
avilla/standard/qq/announcement/capability.py
avilla/standard/qq/announcement/metadata.py
avilla/standard/qq/elements.py
avilla/standard/qq/event.py
avilla/standard/qq/honor/__init__.py
avilla/standard/qq/honor/metadata.py
avilla/standard/qq/util.py
avilla_standard_qq-1.0.0a22.dist-info/METADATA
avilla_standard_qq-1.0.0a22.dist-info/WHEEL
avilla_standard_qq-1.0.0a22.dist-info/licenses/LICENSE
avilla_standard_qq-1.0.0a22.dist-info/RECORD
