Metadata-Version: 2.1
Name: avilla-standard-qq
Version: 1.0.0a22
Home-page: https://github.com/GraiaProject/Avilla
Author-Email: GreyElaina <GreyElaina@outlook.com>, BlueGlassBlock <blueglassblock@outlook.com>, ProgramRipper <programripper@foxmail.com>, RF-Tar-Railt <rf_tar_railt@qq.com>
License: MIT
Project-URL: Homepage, https://github.com/GraiaProject/Avilla
Project-URL: Repository, https://github.com/GraiaProject/Avilla
Requires-Python: >=3.9
